tweakstream/__init__.py
tweakstream/cli.py
tweakstream/config.py
tweakstream/utils.py
tweakstream-0.3.5.dist-info/entry_points.txt
tweakstream-0.3.5.dist-info/LICENSE
tweakstream-0.3.5.dist-info/WHEEL
tweakstream-0.3.5.dist-info/METADATA
tweakstream-0.3.5.dist-info/RECORD
