Metadata-Version: 2.1
Name: tweakstream
Version: 0.3.5
Summary: Stream topics from gathering.tweakers.net
License: MIT
Author: Timo
Requires-Python: >=3.6
Classifier: License :: OSI Approved :: MIT License
Classifier: Programming Language :: Python :: 3
Classifier: Programming Language :: Python :: 3.6
Classifier: Programming Language :: Python :: 3.7
Classifier: Programming Language :: Python :: 3.8
Classifier: Programming Language :: Python :: 3.9
Requires-Dist: appdirs (>=1.4,<2.0)
Requires-Dist: click (>=7.0,<8.0)
Requires-Dist: crayons (>=0.1.2,<0.2.0)
Requires-Dist: tabulate (>=0.8.3,<0.9.0)
Requires-Dist: tweakers (>=0.3.3,<0.4.0)
